annotation/__init__.py
annotation/data_driven_annotation/__init__.py
annotation/data_driven_annotation/cpt.py
annotation/stimulus_driven_annotation/__init__.py
annotation/stimulus_driven_annotation/movies/__init__.py
annotation/stimulus_driven_annotation/movies/annotation_utils.py
annotation/stimulus_driven_annotation/movies/pause_handling.py
annotation/stimulus_driven_annotation/movies/processing_labels.py
annotation/stimulus_driven_annotation/movies/watch_log.py
mock_data/__init__.py
mock_data/mock_data_utils.py
epiphyte-0.1.1.dist-info/LICENSE
epiphyte-0.1.1.dist-info/METADATA
epiphyte-0.1.1.dist-info/WHEEL
epiphyte-0.1.1.dist-info/top_level.txt
epiphyte-0.1.1.dist-info/RECORD
