Metadata-Version: 2.1
Name: epiphyte
Version: 0.1.1
Summary: a Python toolkit for high-dimensional neural data recorded during naturalistic, continuous stimuli
Home-page: https://github.com/mackelab/epiphyte
Author: Alana Darcher, Tamara Mueller
Author-email: alana.darcher@gmail.com
License: UNKNOWN
Platform: UNKNOWN
Classifier: Programming Language :: Python :: 3
Classifier: License :: OSI Approved :: GNU General Public License v3 (GPLv3)
Classifier: Operating System :: OS Independent
Requires-Python: >=3.6
